skperopt/__init__.py
skperopt/search.py
Skperopt-0.0.74.dist-info/LICENSE.txt
Skperopt-0.0.74.dist-info/METADATA
Skperopt-0.0.74.dist-info/WHEEL
Skperopt-0.0.74.dist-info/top_level.txt
Skperopt-0.0.74.dist-info/RECORD
