Metadata-Version: 2.1
Name: Skperopt
Version: 0.0.74
Summary: A hyperopt wrapper - simplifying hyperparameter tuning with Scikit-learn style estimators.
Home-page: https://github.com/lewis-morris/Skperopt
Author: Lewis
Author-email: lewis.morris@gmail.com
License: MIT
Download-URL: https://github.com/lewis-morris/Skperopt/archive/0.0.74.tar.gz
Keywords: hyperopt-wrapper,hyperparameter
Platform: UNKNOWN
Classifier: Development Status :: 5 - Production/Stable
Classifier: Intended Audience :: Developers
Classifier: Intended Audience :: Information Technology
Classifier: Intended Audience :: System Administrators
Classifier: Programming Language :: Python :: 3.6
Classifier: Programming Language :: Python :: 3.7
Classifier: Natural Language :: English
Requires-Dist: numpy
Requires-Dist: pandas
Requires-Dist: sklearn
Requires-Dist: hyperopt (==0.2.3)
